<?xml version="1.0" encoding="UTF-8" standalone="yes"?>
<items>

<item>
<title>[COLOR silver]O Nome da Rosa (1986) [/COLOR]</title>
<link>plugin://plugin.video.elementum/play?uri=magnet:?xt=urn:btih:85edbf21c763ce3bdf065cdae66f4ef06dc97ad4</link>
<thumbnail>https://www.themoviedb.org/t/p/w600_and_h900_bestv2/9co12ykg604MopcYtfvVIh7TN9R.jpg</thumbnail>
<fanart>https://i.imgur.com/YbwYk7G.jpg</fanart>
<info> 
Original: VOD
Lançamento: 1986 / Duração: 2h 11m
Gênero: Ação
Sinopse: Em 1327 William de Baskerville, um monge franciscano, e Adso von Melk, um noviço que o acompanha, chegam a um remoto mosteiro no norte da Itália. 
William de Baskerville pretende participar de um conclave para decidir se a Igreja deve doar parte de suas riquezas, mas a atenção é desviada por vários assassinatos que acontecem no mosteiro
</info>
</item>	
************************************************************************************************************************************
<item>
<title>[COLOR silver]Os Embalos de Sábado à Noite) (1977)[/COLOR]</title>
<link>plugin://plugin.video.elementum/play?uri=magnet:?xt=urn:btih:BYTU74W34Z3U7NH5WROHTHLPPDEQW72L</link>
<thumbnail>https://www.themoviedb.org/t/p/w600_and_h900_bestv2/4vLCcCxyYPn8epEXKp70bqQiFqq.jpg</thumbnail>
<fanart>https://i.imgur.com/YbwYk7G.jpg</fanart>
<info>
Original: VOD
Lançamento: 1977 / Duração: 1h 58m
Gênero: Drama, Música
Sinopse: Tony Manero, um jovem do Brooklyn e um excelente dançarino de disco music, só encontra significado na vida quando dança, pois passar a semana trabalhando em uma loja de tintas não o gratifica de forma nenhuma. 
Assim ele se perfuma, se veste de um jeito fashion e vai para a discoteca no final de semana. 
</info>
</item>
************************************************************************************************************************************

<item>
<title>[COLOR silver]Godzilla vs. Gigan (1972)[/COLOR]</title>
<link>plugin://plugin.video.elementum/play?uri=magnet:?xt=urn:btih:21d0acc0c8f69756ded660fdc480ef4e792d2227</link>
<thumbnail>https://www.themoviedb.org/t/p/w600_and_h900_bestv2/qlrT24kx6GnuzKq3MX4PohhN52E.jpg</thumbnail>
<fanart>https://i.imgur.com/YbwYk7G.jpg</fanart>
<info>
Original: VOD
Lançamento: 1972 / Duração: 1h 28m
Gênero: Ação, Ficção científica
Sinopse: Quando invasores alienígenas planejam um parque temático para crianças com quatro monstros gigantes
para se colidem, o resultado é a inevitável batalha para o destino da Terra

</info>
</item>
********************************************************************************************************************************************************
<item>
<title>[COLOR silver][/COLOR]</title>
<link>plugin://plugin.video.elementum/play?uri=magnet:?xt=urn:btih:</link>
<thumbnail></thumbnail>
<fanart>https://i.imgur.com/YbwYk7G.jpg</fanart>
<info>
Original: VOD
Lançamento: 2022.
Sinopse:

</info>
</item>
********************************************************************************************************************************************************



</items>